setup.py
pyucsc.egg-info/PKG-INFO
pyucsc.egg-info/SOURCES.txt
pyucsc.egg-info/dependency_links.txt
pyucsc.egg-info/requires.txt
pyucsc.egg-info/top_level.txt
ucsc/__init__.py
ucsc/config.py
ucsc/db.py
ucsc/model.py
ucsc/util.py