Metadata-Version: 1.1
Name: pyucsc
Version: 0.2
Summary: Bindings to UCSC genome browser tables
Home-page: UNKNOWN
Author: James Casbon
Author-email: james.casbon@popgentech.com
License: License :: OSI Approved :: BSD License
Keywords: bioinformatics ucsc genome
Platform: UNKNOWN
Classifier: Development Status :: 4 - Beta
Classifier: Intended Audience :: Developers
Classifier: Intended Audience :: Science/Research
Classifier: Programming Language :: Python
Classifier: Topic :: Scientific/Engineering
